Metadata-Version: 2.1
Name: pyswigex
Version: 0.0.3
Summary: Ready-to-use complete example of a cross-platform Python source package built from C++ library using SWIG and doxygen
Home-page: https://github.com/fabien-ors/pyswigex
Author: Fabien Ors
Author-email: fabien.ors@mines-paristech.fr
License: UNKNOWN
Project-URL: Bug Tracker, https://github.com/fabien-ors/pyswigex/issues
Platform: UNKNOWN
Classifier: Programming Language :: Python :: 3
Classifier: Development Status :: 4 - Beta
Classifier: Environment :: Other Environment
Classifier: Intended Audience :: Developers
Classifier: License :: OSI Approved :: MIT License
Classifier: Operating System :: OS Independent
Classifier: Topic :: Software Development :: Libraries :: Python Modules
Requires-Python: >=3
License-File: LICENSE
